CHANGES.txt
MANIFEST.in
README.md
setup.py
MailApi.egg-info/PKG-INFO
MailApi.egg-info/SOURCES.txt
MailApi.egg-info/dependency_links.txt
MailApi.egg-info/not-zip-safe
MailApi.egg-info/requires.txt
MailApi.egg-info/top_level.txt
mailapi/__init__.py
mailapi/alias.py
mailapi/db.py
mailapi/domain.py
mailapi/exc.py
mailapi/helpers.py
mailapi/mailbox.py
mailapi/maildir.py
mailapi/md5crypt.py
mailapi/models.py
mailapi/password.py
mailapi/validators.py
mailapi/tests/__init__.py
mailapi/tests/test_aliases.py
mailapi/tests/test_domains.py
mailapi/tests/test_helpers.py
mailapi/tests/test_mailboxes.py