Metadata-Version: 1.1
Name: MailApi
Version: 0.1.4
Summary: An interface to iredadmin
Home-page: UNKNOWN
Author: Paul Szabo
Author-email: paul@cupromotions.ca
License: UNKNOWN
Keywords: iredadmin iredmail email api
Platform: UNKNOWN
Classifier: Programming Language :: Python
Classifier: Programming Language :: Python :: 2.7
